{
  "player1Name": "Alice",
  "player2Name": "Bob",
  "player1": {
    "lifeTotal": 20,
    "hand": ["Formidable Speaker", "Bark of Doran"],
    "battlefield": [
      {"name": "Forest"},
      {"name": "Forest"},
      {"name": "Forest"},
      {"name": "Forest", "tapped": true}
    ],
    "graveyard": [],
    "library": [
      "Great Forest Druid",
      "Bloom Tender",
      "Surly Farrier",
      "Bristlebane Battler",
      "Forest"
    ]
  },
  "player2": {
    "lifeTotal": 20,
    "hand": [],
    "battlefield": [
      {"name": "Forest"},
      {"name": "Forest"}
    ],
    "graveyard": [],
    "library": ["Forest", "Forest", "Forest"]
  },
  "phase": "PRECOMBAT_MAIN",
  "activePlayer": 1,
  "priorityPlayer": 1,
  "player1StopAtSteps": [],
  "player2StopAtSteps": [],
  "player1OpponentStopAtSteps": [],
  "player2OpponentStopAtSteps": []
}
