{
  "player1Name": "Alice",
  "player2Name": "Bob",
  "player1": {
    "lifeTotal": 20,
    "hand": [],
    "battlefield": [
      {
        "name": "Essence Channeler",
        "counters": {
          "PLUS_ONE_PLUS_ONE": 1,
          "GOLD": 2,
          "CHARGE": 1
        }
      },
      {"name": "Grizzly Bears"},
      {"name": "Plains"},
      {"name": "Plains"}
    ],
    "graveyard": [],
    "library": ["Plains", "Plains", "Plains"]
  },
  "player2": {
    "lifeTotal": 20,
    "hand": ["Shock"],
    "battlefield": [
      {"name": "Mountain"},
      {"name": "Mountain"}
    ],
    "graveyard": [],
    "library": ["Mountain", "Mountain", "Mountain"]
  },
  "phase": "PRECOMBAT_MAIN",
  "activePlayer": 1,
  "priorityPlayer": 2,
  "player1StopAtSteps": [],
  "player2StopAtSteps": []
}
